<?xml version="1.0" encoding="UTF-8"?>
<?xml-stylesheet type="text/xsl" href="declension_tables.xsl" ?>
<grammar_tables title="Latin">
    <description>Note "(&lt;)" abbreviates "(fused with last stem sound (consonant or vowel))", "(&lt;&lt;)" abbreviates "(fused with last stem vowel + consonant)", "(–)" abbreviates "(previous vowel is lengthened)".</description>
    <grammar_table id="proto-italic" title="proto-italic">
        <description>Note that <source book="Sihler" /> p. 286 names -fos as the Proto-Italic dative-ablative consonant stem plural ending, but this (even if reflected in all other Italic languages) is inconsistent with Early Latin's reflex of original -bʰos as -bos (<source book="Sihler" /> p. 147, 286), so the earlier form is here given.
The dative singular is somewhat aritrarily chosen as the proto-italic starting point for the fusion of consonant and i-stem paradigms (<source book="Sihler" /> p. 316, 318), with other forms still separate. 
The i-stem genitive singular is unsure, at least the one continued in Latin (<source book="Sihler" /> p. 316-317).
Not depicted: neuter r/n-stems (<source book="Sihler" /> p. 298-299).
</description>
        <declension_def id="sg" short_title="singular">
            <declension_def id="sg-a" title="singular a-stem" short_title="a" />
            <declension_def id="sg-o" title="singular o-stem" short_title="o">
                <declension_def id="sg-o-mf" title="singular o-stem animate" short_title="mf" />
                <declension_def id="sg-o-n" title="singular o-stem inanimate" short_title="n" />
            </declension_def>
            <declension_def id="sg-athem" title="singular athematic stem">
                <declension_def id="sg-c" title="singular consonant stem" short_title="consonant">
                    <declension_def id="sg-c-mf" title="singular animate consonant stem" short_title="mf">
                        <declension_def id="sg-c-mf-d" title="singular animate consonant stem in dental" short_title="-(d|t)-" />
                        <declension_def id="sg-c-mf-r" title="singular animate consonant stem in -r/-l" short_title="-r-" />
                        <declension_def id="sg-c-mf-n" title="singular animate consonant stem in vowel + n" short_title="-n-" />
                        <declension_def id="sg-c-mf--" title="singular animate consonant stem not in vowel + -r/-n or dental" short_title="&amp;c" />
                    </declension_def>
                    <declension_def id="sg-c-n" title="singular inanimate consonant stem" short_title="n">
                        <declension_def id="sg-c-n-n" title="singular inanimate consonant stem in -n" short_title="-n-" />
                        <declension_def id="sg-c-n-s" title="singular inanimate consonant stem in -s" short_title="-s-" />
                        <declension_def id="sg-c-n-r" title="singular inanimate consonant stem in -r" short_title="-r-" />
                        <declension_def id="sg-c-n--" title="singular inanimate consonant stem not in -n" short_title="&amp;c" />
                     </declension_def>
                </declension_def>
                <declension_def id="sg-i" title="singular i-stem" short_title="i">
                    <declension_def id="sg-i-mf" title="singular animate i-stem" short_title="mf" />
                    <declension_def id="sg-i-n" title="singular inanimate i-stem" short_title="n" />
                </declension_def>
            </declension_def>
        </declension_def>
        <declension_def id="pl" short_title="plural">
            <declension_def id="pl-a" title="plural a-stem" short_title="a" />
            <declension_def id="pl-o" title="plural o-stem" short_title="o">
                <declension_def id="pl-o-mf" title="plural animate o-stem" short_title="mf" />
                <declension_def id="pl-o-n" title="plural inanimate o-stem" short_title="n" />
            </declension_def>
            <declension_def id="pl-c" title="plural consonant stem" short_title="consonant">
                <declension_def id="pl-c-mf" title="plural animate consonant stem" short_title="mf" />
                <declension_def id="pl-c-n" title="plural inanimate consonant stem" short_title="n" />
            </declension_def>
            <declension_def id="pl-i" title="plural i-stem" short_title="i">
                <declension_def id="pl-i-mf" title="plural animate i-stem" short_title="mf" />
                <declension_def id="pl-i-n" title="plural inanimate i-stem" short_title="n" />
            </declension_def>
        </declension_def>
        <case_def id="NVAc" title="nominative-vocative-accusative">
            <case_def id="NV" title="nominative-vocative">
                <case_def id="N" title="nominative" short_title="N" />
                <case_def id="V" title="vocative" short_title="V" />
            </case_def>
            <case_def id="Ac" title="accusative" short_title="Ac" />
        </case_def>
        <case_def id="DAb" title="dative-ablative">
            <case_def id="D" title="dative" short_title="D" />
            <case_def id="Ab" title="ablative" short_title="Ab" />
        </case_def>
        <case_def id="G" title="genitive" short_title="G" />
        <case_def id="L" title="locative" short_title="L" />
        <paradigm declension="sg-c-mf-d" case="NV" form="fused-ss" footnote="sg-c-mf-nv-d0"/>
        <paradigm declension="sg-c-mf-r" case="NV" form="0" footnote="sg-c-mf-nv-r"/>
        <paradigm declension="sg-c-mf-n" case="NV" form="double-fused-o:" footnote="sg-c-mf-nv-n"/>
        <paradigm declension="sg-c-mf--" case="NV" form="s" footnote="sg-c-mf-nv"/>
        <paradigm declension="sg-c-mf" case="Ac" form="em" footnote="sg-c-mf-ac"/>
        <paradigm declension="sg-c-n-n" case="NVAc" form="double-fused-en" footnote="sg-c-n-n" />
        <paradigm declension="sg-c-n-s" case="NVAc" form="double-fused-os-0" footnote="sg-c-n-s" />
        <paradigm declension="sg-c-n-r" case="NVAc" form="0" footnote="sg-c-n-r0" />
        <paradigm declension="sg-c-n--" case="NVAc" form="fused-0" footnote="sg-c-n--" />
        <paradigm declension="sg-i-n" case="NVAc" form="0" footnote="sg-i-n" />
        <paradigm declension="sg-i-mf" case="NV" form="s" footnote="sg-i-mf--" />
        <paradigm declension="sg-i-mf" case="Ac" form="m" footnote="sg-i-mf-ac" />
        <paradigm declension="sg-c" case="D" form="ei" footnote="sg-c-d" />
        <paradigm declension="sg-i" case="D" form="fused-ei" footnote="sg-i-d" />
        <paradigm declension="sg-c" case="Ab" form="(e:|i:)d" footnote="sg-c-ab0" />
        <paradigm declension="sg-i" case="Ab" form="fused-i:d" footnote="sg-i-ab0" />
        <paradigm declension="sg-c" case="G" form="(e|o)s" footnote="sg-c-g" />
        <paradigm declension="sg-i" case="G" form="fused-eis-es" footnote="sg-i-g" />
        <paradigm declension="sg-c" case="L" form="i" footnote="sg-c-l0" />
        <paradigm declension="sg-a" case="N" form="a:" footnote="sg-a-n0"/>
        <paradigm declension="sg-a" case="V" form="a:" footnote="sg-a-v0"/>
        <paradigm declension="sg-a" case="Ac" form="a:?m" footnote="sg-a-ac"/>
        <paradigm declension="sg-a" case="D" form="a:i" footnote="sg-a-d"/>
        <paradigm declension="sg-a" case="Ab" form="a:d" footnote="sg-a-ab0"/>
        <paradigm declension="sg-a" case="G" form="a:s" footnote="sg-a-g"/>
        <paradigm declension="sg-a" case="L" form="a:i" footnote="sg-a-l"/>
        <paradigm declension="sg-o-mf" case="N" form="os" footnote="sg-o-mf-n"/>
        <paradigm declension="sg-o-mf" case="V" form="e" footnote="sg-o-mf-n"/>
        <paradigm declension="sg-o-n" case="NVAc" form="om" footnote="sg-o-n-ac"/>
        <paradigm declension="sg-o-mf" case="Ac" form="om" footnote="sg-o-n-ac"/>
        <paradigm declension="sg-o" case="D" form="o:i" footnote="sg-o-d"/>
        <paradigm declension="sg-o" case="Ab" form="o:d" footnote="sg-o-ab0"/>
        <paradigm declension="sg-o" case="G" form="osio" footnote="sg-o-gA"/>
        <paradigm declension="sg-o" case="L" form="(o/e)i" footnote="sg-o-l"/>
        <paradigm declension="pl-a" case="NV" form="a:s" footnote="pl-a-n"/>
        <paradigm declension="pl-a" case="Ac" form="a:ns" footnote="pl-a-ac"/>
        <paradigm declension="pl-a" case="DAb" form="a:is" footnote="pl-a-dab"/>
        <paradigm declension="pl-a" case="G" form="a:so:m" footnote="pl-a-g"/>
        <paradigm declension="pl-o-mf" case="NV" form="o:s" footnote="pl-o-mf-n"/>
        <paradigm declension="pl-o-mf" case="Ac" form="ons" footnote="pl-o-mf-ac"/>
        <paradigm declension="pl-o-n" case="NVAc" form="a:" footnote="pl-o-n-ac"/>
        <paradigm declension="pl-o" case="DAb" form="ois" footnote="pl-o-dab"/>
        <paradigm declension="pl-o" case="G" form="om" footnote="pl-o-g0"/>
        <paradigm declension="pl-c-n" case="NVAc" form="a:" footnote="pl-c-n"/>
        <paradigm declension="pl-c-mf" case="NV" form="es" footnote="pl-c-nv"/>
        <paradigm declension="pl-c-mf" case="Ac" form="ens" footnote="pl-c-ac"/>
        <paradigm declension="pl-c" case="DAb" form="bhos" footnote="pl-c-dab0"/>
        <paradigm declension="pl-c" case="G" form="om" footnote="pl-c-g0"/>
        <paradigm declension="pl-i" case="DAb" form="bhos" footnote="pl-i-dab"/>
        <paradigm declension="pl-i" case="G" form="om" footnote="pl-i-g"/>
        <paradigm declension="pl-i-mf" case="NV" form="fused-eies" footnote="pl-i-nv"/>
        <paradigm declension="pl-i-mf" case="Ac" form="ins" footnote="pl-i-ac"/>
        <paradigm declension="pl-i-n" case="NVAc" form="fused-i:" footnote="pl-i-n"/>
    </grammar_table>
    <grammar_table id="classical" title="classical">
        <description>
-o- becomes -u- before final consonants (<source book="Sihler" /> p. 66),
-e- becomes -i- before non-nasal consonants (general rule with some exception, but holds true before any final consonants) (<source book="Sihler" /> p. 65),
nominative/vocative -ros/-re/-ris becomes -r after vowels (not for i-stems) and -er after consonants (<source book="Sihler" /> p. 70),
vocative -ie and genitive -iī become -ī (<source book="Sihler" /> p. 256, 260),
dative -ōi and ablative -ōd become -ō (<source book="Sihler" /> p. 58, 228),
word-final -ns becomes -s with lengthening of preceding vocal (<source book="Sihler" /> p. 215),
-ā becomes -a (<source book="Sihler" /> p. 78),
introduction of singular genitive in -ī (<source book="Sihler" /> p. 260),
-ois becomes -eis becomes -īs (<source book="Sihler" /> p. 263), same with -āis (<source book="Sihler" /> p. 272),
o-stem genitive plural partly modeled after a-stem (<source book="Sihler" /> p. 264),
o-stem nominative plural is replaced from the pronoun -oi becoming -ei becoming -ī (<source book="Sihler" /> p. 260),
same with a-stem nominative plural (<source book="Sihler" /> p. 271),
long vowels before -m got short (<source book="Sihler" /> p. 78),
-āi shortened to -ae (<source book="Sihler" /> p. 268),
loss of word-final -d after a long vowel (<source book="Sihler" /> p. 228),
in a-stem plural dative-ablative –īs is replaced with -ābus where necessary to avoid homophony with o-stem plural dative-ablatives (<source book="Sihler" /> p. 272),
intervocalic -s becomes -r (<source book="Sihler" /> p. 171-172),
word-final -ss becomes -s (<source book="Sihler" /> p. 204-205),
dorsal stop plus -s becomes -x (<source book="Sihler" /> p. 204),
-ei- in final syllable becomes -ī (<source book="Sihler" /> p. 70),
final -i becomes -e (<source book="Sihler" /> p. 65),
either the consonant locative or (less likely) instrumental singular becomes the consonant ablative singular (<source book="Sihler" /> p. 285),
consonant locative singular in -ī is modeled in analogy to o-stems (<source book="Sihler" /> p. 285),
the -bus derived from the -b- reflex to word-internal -bʰ- (<source book="Sihler" /> p. 145, 147) and got an -i- prefix (<source book="Sihler" /> p. 286),
the i-stem plural nominative ending -ēs becomes the consonant plural nominative ending proper (<source book="Sihler" /> p. 286),
-rs becomes -rr becomes in final position -r (<source book="Sihler" /> p. 211),
former root stems in -s whose -s- became -r- intervocalic sometimes retain -s in the nominative singular (<source book="Sihler" /> p. 310-311),
long vowels before final non-s consonants shorten (<source book="Sihler" /> p. 79),
l-stems emerge from other stem-forms (-n-, -l/n-) (<source book="Sihler" /> p. 304),
some neuter s-stems (notable exception: root nouns) analogize the rhotacized stem ending (-r-) to the nominative singular (<source book="Sihler" /> p. 306, 309)
the -on- suffix of consonant stems is reflected as medial -in- (<source book="Sihler" /> p. 60-61, 295-296),
consonant stem endings encroach on i-stem endings (<source book="Sihler" /> p. 318),
i-stems in -nd-, -nt-, -rt- end in -s (&lt;&lt;), with lengthening of preceding vowel if -ns results (<source book="Sihler" /> p. 316),
i-stem neuter nominative/vocative singulars lost their end vowel on mono-syllabic stems (<source book="Sihler" /> p. 69),
i-stem genitive singular -is evolves either from consonant stem encroachment or an original ending in -es (<source book="Sihler" /> p. 316-317),
certain animate n-stem nouns with nominative singular in -en emerge from gender change, compounds with the weakened root "can-", and unclear etymology (<source book="Sihler" /> p.296, 298),
i-stem plural animate nominative/vocative -eies becomes -ees (loss of intervocalic -i-, <source book="Sihler" /> p. 188) becomes -ēs (<source book="Sihler" /> p. 317),
i-stem plural inaminate nominative/vocative/accusative gets the consonant ending -a appended (<source book="Sihler" /> p. 317),
long vowels shorten before other vowels (<source book="Sihler" /> p. 80).
Not depicted relationship: animate i-stem nouns with accusative singular in -im always form the ablative singular to -ī (<source book="Sihler" /> p. 316).
Not depicted: kinship nouns of animate consonant stems in -r with nominative singular in -er (&lt;) (like "pater"/"patris") (<source book="Sihler" /> p. 293).
Not depicted: The consonant stems in -n- freak cases of "carō"/"carnis", "iuvenis"/"iuvenis", "sangu(i|ī)s"/"sanguinis", "liēn"/"li(e|ē)nis", "fel"/"fellis" (<source book="Sihler" /> p. 291, 295-296, 298).
Not depicted: The consonant stems in -l- freak cases of "sāl"/"salis", "fel"/"fellis", "mel"/"mellis" (<source book="Sihler" /> p. 304).
Not depicted: The root noun freak cases of "vīs" and "spēs"/"speī" (<source book="Sihler" /> p. 311).
Not depicted: Neuter r/n-stems freak cases of "femur"/"feminis", "iecur"/"iocineris", "iter"/"itineris" <source book="Sihler" /> p. 298-299).
Not depcited: Nouns in -ēs nominative singular, mostly behaving like i-stem nouns (<source book="Sihler" /> p. 316).
A locative plural in -īs is too speculative (<source book="Sihler" /> p. 253 alone mentions it, prefixed with a "perhaps") to include in the table.</description>
        <declension_def id="sg" short_title="singular">
            <declension_def id="sg-a" title="singular a-stem" short_title="a" />
            <declension_def id="sg-o" title="singular o-stem" short_title="o">
                <declension_def id="sg-o-mf" title="singular o-stem animate" short_title="mf">
                    <declension_def id="sg-ro-mf" title="singular o-stem (in -r) animate" >
                        <declension_def id="sg-cro-mf" title="singular o-stem (in consonant + -r) animate" short_title="-Cr-" />
                        <declension_def id="sg-vro-mf" title="singular o-stem (in vowel + -r) animate" short_title="-Vr-" />
                    </declension_def>
                    <declension_def id="sg--o-mf" title="singular o-stem animate">
                        <declension_def id="sg-io-mf" title="singular o-stem (in -i) animate" short_title="-i-" />
                        <declension_def id="sg---o-mf" title="singular o-stem (not in -i) animate" short_title="&amp;c" />
                    </declension_def>
                </declension_def>
                <declension_def id="sg-o-n" title="singular o-stem inanimate" short_title="n" >
                    <declension_def id="sg-io-n" title="singular o-stem inanimate in -i" short_title="-i-" />
                    <declension_def id="sg--o-n" title="singular o-stem inanimate (not in -i)" short_title="&amp;c" />
                </declension_def>
            </declension_def>
            <declension_def id="sg-athem" title="singular athematic stem">
                <declension_def id="sg-c" title="singular consonant stem" short_title="consonant">
                    <declension_def id="sg-c-mf" title="singular animate consonant stem" short_title="mf">
                        <declension_def id="sg-c-mf-d+" title="singular animate consonant stem in dental and some stems in -r formerly in -s"
                                        short_title="-(d|t)-, some -(s&gt;r)-" />
                        <declension_def id="sg-c-mf-g" title="singular animate consonant stem in dorsal" short_title="-(g|c)-" />
                        <declension_def id="sg-c-mf-rl" title="singular animate consonant stem in -r/-l" short_title="-(r|l)-" />
                        <declension_def id="sg-c-mf-ro" title="singular animate consonant stem in -ōr" short_title="-ōr-" />
                        <declension_def id="sg-c-mf-n" title="singular animate consonant stem in -n" short_title="-n-" />
                        <declension_def id="sg-c-mf-n-freak" title="singular animate consonant stem in -in (freak cases)" short_title="some -in-" />
                        <declension_def id="sg-c-mf--" title="singular animate consonant stem not in dental, dorsal, or -r/-n" short_title="&amp;c" />
                    </declension_def>
                    <declension_def id="sg-c-n" title="singular inanimate consonant stem" short_title="n">
                        <declension_def id="sg-c-n-n" title="singular inanimate consonant stem in -n" short_title="-n-" />
                        <declension_def id="sg-c-n-s" title="singular inanimate consonant stem in -r formerly in -s" short_title="-(s&gt;r)-" />
                        <declension_def id="sg-c-n-r" title="singular inanimate consonant stem in -r (not -rr-)" short_title="-r- not -rr-" />
                        <declension_def id="sg-c-n--" title="singular inanimate consonant stem not in -n" short_title="&amp;c" />
                    </declension_def>
                </declension_def>
                <declension_def id="sg-i" title="singular i-stem" short_title="i">
                    <declension_def id="sg-i-mf" title="singular animate i-stem" short_title="mf">
                        <declension_def id="sg-i-mf-ndnt" title="singular animate i-stem in -nd-, -nt-" short_title="-n(d|t)i-" />
                        <declension_def id="sg-i-mf-rt" title="singular animate i-stem in -rt-" short_title="-rti-" />
                        <declension_def id="sg-i-mf-Cr" title="singular animate i-stem in consonant + -r-" short_title="-Cri-" />
                        <declension_def id="sg-i-mf--" title="singular animate i-stem" short_title="&amp;c" />
                    </declension_def>
                    <declension_def id="sg-i-n" title="singular inanimate i-stem" short_title="n">
                        <declension_def id="sg-i-n-mono" title="singular inanimate i-stem (mono-syllabic)" short_title="mono" />
                        <declension_def id="sg-i-n-poly" title="singular inanimate i-stem (poly-syllabic)" short_title="poly" />
                    </declension_def>
                </declension_def>
            </declension_def>
        </declension_def>
        <declension_def id="pl" short_title="plural">
            <declension_def id="pl-a" title="plural a-stem" short_title="a" />
            <declension_def id="pl-o" title="plural o-stem" short_title="o">
                <declension_def id="pl-o-mf" title="plural animate o-stem" short_title="mf" />
                <declension_def id="pl-o-n" title="plural inanimate o-stem" short_title="n" />
            </declension_def>
            <declension_def id="pl-c" title="plural consonant stem" short_title="cons.">
                <declension_def id="pl-c-mf" title="plural animate consonant stem" short_title="mf" />
                <declension_def id="pl-c-n" title="plural inanimate consonant stem" short_title="n" />
            </declension_def>
            <declension_def id="pl-i" title="plural i-stem" short_title="i">
                <declension_def id="pl-i-mf" title="plural animate i-stem" short_title="mf" />
                <declension_def id="pl-i-n" title="plural inanimate i-stem" short_title="n" />
            </declension_def>
        </declension_def>
        <case_def id="NVAc" title="nominative-vocative-accusative">
            <case_def id="NV" title="nominative-vocative">
                <case_def id="N" title="nominative" short_title="N" />
                <case_def id="V" title="vocative" short_title="V" />
            </case_def>
            <case_def id="Ac" title="accusative" short_title="Ac" />
        </case_def>
        <case_def id="DAb" title="dative-ablative">
            <case_def id="D" title="dative" short_title="D" />
            <case_def id="Ab" title="ablative" short_title="Ab" />
        </case_def>
        <case_def id="G" title="genitive" short_title="G" />
        <case_def id="L" title="locative" short_title="L" />
        <paradigm declension="sg-a" case="N" form="a" footnote="sg-a-n"/>
        <paradigm declension="sg-a" case="V" form="a" footnote="sg-a-v"/>
        <paradigm declension="sg-a" case="Ac" form="am" footnote="sg-a-ac"/>
        <paradigm declension="sg-a" case="D" form="ae" footnote="sg-a-d"/>
        <paradigm declension="sg-a" case="Ab" form="a:d?" footnote="sg-a-ab"/>
        <paradigm declension="sg-a" case="G" form="a:s|ae" footnote="sg-a-g"/>
        <paradigm declension="sg-a" case="L" form="ae" footnote="sg-a-l"/>
        <paradigm declension="sg-io-mf" case="N" form="us" footnote="sg-o-mf-n"/>
        <paradigm declension="sg-io-mf" case="V" form="fused-i:" footnote="sg-o-mf-n"/>
        <paradigm declension="sg-cro-mf" case="NV" form="fused-er" footnote="sg-ro-mf-n"/>
        <paradigm declension="sg-vro-mf" case="NV" form="0" footnote="sg-ro-mf-n"/>
        <paradigm declension="sg--o-mf" case="N" form="us" footnote="sg-o-mf-n"/>
        <paradigm declension="sg---o-mf" case="V" continues="proto-italic sg-o-mf V" />
        <paradigm declension="sg-o-n" case="NVAc" form="um" footnote="sg-o-n-ac"/>
        <paradigm declension="sg-o-mf" case="Ac" form="um" footnote="sg-o-n-ac"/>
        <paradigm declension="sg-o" case="D" form="o:" footnote="sg-o-d"/>
        <paradigm declension="sg-o" case="Ab" form="o:" footnote="sg-o-ab"/>
        <paradigm declension="sg-ro-mf" case="G" form="i:" footnote="sg-o-gB"/>
        <paradigm declension="sg---o-mf" case="G" form="i:" footnote="sg-o-gB"/>
        <paradigm declension="sg-io-mf" case="G" form="fused-i:" footnote="sg-o-gB"/>
        <paradigm declension="sg-io-n" case="G" form="fused-i:" footnote="sg-o-gB"/>
        <paradigm declension="sg--o-n" case="G" form="i:" footnote="sg-o-gB"/>
        <paradigm declension="sg-o" case="L" form="i:" footnote="sg-o-l"/>
        <paradigm declension="sg-c-mf--" case="NV" continues="proto-italic sg-c-mf-- NV" />
        <paradigm declension="sg-c-mf-d+" case="NV" form="fused-s" footnote="sg-c-mf-nv-d+"/>
        <paradigm declension="sg-c-mf-g" case="NV" form="fused-x" footnote="sg-c-mf-nv-g"/>
        <paradigm declension="sg-c-mf-rl" case="NV" form="0" footnote="sg-c-mf-nv-rl"/>
        <paradigm declension="sg-c-mf-ro" case="NV" form="double-fused-or" footnote="sg-c-mf-ro-NV" />
        <paradigm declension="sg-c-mf-n" case="NV" continues="proto-italic sg-c-mf-n NV" />
        <paradigm declension="sg-c-mf-n-freak" case="NV" form="double-fused-en" footnote="sg-c-mf-n-freak" />
        <paradigm declension="sg-c-mf" case="Ac" continues="proto-italic sg-c-mf Ac" />
        <paradigm declension="sg-c-n--" case="NVAc" continues="proto-italic sg-c-n-- NVAc" />
        <paradigm declension="sg-c-n-n" case="NVAc" continues="proto-italic sg-c-n-n NVAc" />
        <paradigm declension="sg-c-n-s" case="NVAc" form="double-fused-u(r|s)-fused-s" footnote="sg-c-n-s" />
        <paradigm declension="sg-c-n-r" case="NVAc" form="0" footnote="sg-c-n-r" />
        <paradigm declension="sg-i-mf--" case="NV" continues="proto-italic sg-i-mf NV" />
        <paradigm declension="sg-i-mf-Cr" case="NV" form="double-fused-er" footnote="sg-i-mf-Cr" />
        <paradigm declension="sg-i-mf-ndnt" case="NV" form="lengthening-double-fused-s" footnote="sg-i-mf-ndntrt" />
        <paradigm declension="sg-i-mf-rt" case="NV" form="double-fused-s" footnote="sg-i-mf-ndntrt" />
        <paradigm declension="sg-i-mf" case="Ac" form="fused-em-m" footnote="sg-i-mf-ac" />
        <paradigm declension="sg-i-n-mono" case="NVAc" form="fused-e" footnote="sg-i-n" />
        <paradigm declension="sg-i-n-poly" case="NVAc" form="fused-0" footnote="sg-i-n-poly" />
        <paradigm declension="sg-c" case="D" form="i:" footnote="sg-c-d" />
        <paradigm declension="sg-i" case="D" form="fused-i:" footnote="sg-i-d" />
        <paradigm declension="sg-c" case="Ab" form="e" footnote="sg-c-ab" />
        <paradigm declension="sg-i" case="Ab" form="fused-e|i:" footnote="sg-i-ab" />
        <paradigm declension="sg-c" case="G" form="(i|u)s" footnote="sg-c-g" />
        <paradigm declension="sg-i" case="G" form="s" footnote="sg-i-g" />
        <paradigm declension="sg-c" case="L" form="e|i:" footnote="sg-c-l" />
        <paradigm declension="pl-a" case="NV" form="ae" footnote="pl-a-n"/>
        <paradigm declension="pl-a" case="Ac" form="a:s" footnote="pl-a-ac"/>
        <paradigm declension="pl-a" case="DAb" form="i:s|a:bus" footnote="pl-a-dab"/>
        <paradigm declension="pl-a" case="G" form="a:rum" footnote="pl-a-g"/>
        <paradigm declension="pl-o-mf" case="NV" form="i:" footnote="pl-o-mf-n"/>
        <paradigm declension="pl-o-mf" case="Ac" form="o:s" footnote="pl-o-mf-ac"/>
        <paradigm declension="pl-o-n" case="NVAc" form="a" footnote="pl-o-n-ac"/>
        <paradigm declension="pl-o" case="DAb" form="i:s" footnote="pl-o-dab"/>
        <paradigm declension="pl-o" case="G" form="(o:r)um" footnote="pl-o-g"/>
        <paradigm declension="pl-c-mf" case="NV" form="e:s" footnote="pl-c-nv"/>
        <paradigm declension="pl-c-mf" case="Ac" form="e:s" footnote="pl-c-ac"/>
        <paradigm declension="pl-c-n" case="NVAc" form="a" footnote="pl-c-n"/>
        <paradigm declension="pl-c" case="DAb" form="ibus" footnote="pl-c-dab"/>
        <paradigm declension="pl-c" case="G" form="um" footnote="pl-c-g"/>
        <paradigm declension="pl-i-mf" case="NVAc" form="fused-i:s-fused-e:s" footnote="pl-i-nvac"/>
        <paradigm declension="pl-i-n" case="NVAc" form="a" footnote="pl-i-n"/>
        <paradigm declension="pl-i" case="DAb" form="bus" footnote="pl-i-dab"/>
        <paradigm declension="pl-i" case="G" form="um" footnote="pl-i-g"/>
    </grammar_table>
    <forms>
        <form id="fused-eies">-eies (&lt;)</form>
        <form id="fused-i:s-fused-e:s">-īs (&lt;), -ēs (&lt;)</form>
        <form id="lengthening-double-fused-s">-s (–) (&lt;&lt;)</form>
        <form id="double-fused-s">-s (&lt;&lt;)</form>
        <form id="double-fused-os-0">-os (&lt;&lt;), -∅</form>
        <form id="double-fused-u(r|s)-fused-s">-u(r|s) (&lt;&lt;), -s (&lt;)</form>
        <form id="double-fused-or">-or (&lt;&lt;)</form>
        <form id="double-fused-o:">-ō (&lt;&lt;)</form>
        <form id="0">-∅</form>
        <form id="es">-es</form>
        <form id="double-fused-en">-en (&lt;&lt;)</form>
        <form id="ens">-ens</form>
        <form id="e:s">-ēs</form>
        <form id="ibus">-ibus</form>
        <form id="bhos">-bʰos</form>
        <form id="fused-e">-e (&lt;)</form>
        <form id="fused-0">-∅ (&lt;)</form>
        <form id="s">-s</form>
        <form id="fused-s">-s (&lt;)</form>
        <form id="fused-x">-x (&lt;)</form>
        <form id="fused-ss">-ss (&lt;)</form>
        <form id="em">-em</form>
        <form id="ei">-ei</form>
        <form id="fused-ei">-ei (&lt;)</form>
        <form id="fused-em-m">-em (&lt;), -m</form>
        <form id="fused-eis-es">-eis (&lt;), -es</form>
        <form id="(e:|i:)d">-(ē|ī)d</form>
        <form id="(e|o)s">-(e|o)s</form>
        <form id="i">-i</form>
        <form id="ins">-ins</form>
        <form id="(i|u)s">-(i|u)s</form>
        <form id="e|i:">-(e|ī)</form>
        <form id="fused-e|i:">-(e|ī) (&lt;)</form>
        <form id="a:">-ā</form>
        <form id="a">-a</form>
        <form id="a:?m">-(a|ā)m</form>
        <form id="am">-am</form>
        <form id="bus">-bus</form>
        <form id="a:i">-āi</form>
        <form id="a:d">-ād</form>
        <form id="a:d?">-ā?(d)</form>
        <form id="a:s">-ās</form>
        <form id="a:ns">-āns</form>
        <form id="a:is">-āis</form>
        <form id="a:so:m">-āsōm</form>
        <form id="a:s|ae">-ās, -ae</form>
        <form id="i:s|a:bus">-īs, -ābus</form>
        <form id="a:rum">-ārum</form>
        <form id="ae">-ae</form>
        <form id="e">-e</form>
        <form id="m">-m</form>
        <form id="os">-os</form>
        <form id="om">-om</form>
        <form id="o:i">-ōi</form>
        <form id="o:">-ō</form>
        <form id="o:d">-ōd</form>
        <form id="osio">-osio</form>
        <form id="(o/e)i">-(o|e)i</form>
        <form id="ois">-ois</form>
        <form id="us">-us</form>
        <form id="fused-er">-er (&lt;)</form>
        <form id="double-fused-er">-er (&lt;&lt;)</form>
        <form id="fused-i:">-ī (&lt;)</form>
        <form id="0">-∅</form>
        <form id="um">-um</form>
        <form id="i:">-ī</form>
        <form id="ons">-ons</form>
        <form id="o:s">-ōs</form>
        <form id="i:s">-īs</form>
        <form id="fused-i:d">-īd (&lt;)</form>
        <form id="(o:r)um">-ōrum, -um</form>
    </forms>
    <footnotes>
        <footnote id="sg-c-n--"><source book="Sihler" /> p. 284</footnote>
        <footnote id="sg-c-n-n"><source book="Sihler" /> p. 297</footnote>
        <footnote id="sg-c-n-r0"><source book="Sihler" /> p. 293</footnote>
        <footnote id="sg-c-n-r"><source book="Sihler" /> p. 293, 306</footnote>
        <footnote id="sg-c-n-s"><source book="Sihler" /> p. 305-307</footnote>
        <footnote id="sg-c-mf-nv"><source book="Sihler" /> p. 283</footnote>
        <footnote id="sg-c-mf-nv-d0"><source book="Fortson" /> p. 277, <source book="Sihler" /> p. 204, 283</footnote>
        <footnote id="sg-c-mf-nv-d+"><source book="Sihler" /> p. 204-205, 283,, 309-311</footnote>
        <footnote id="sg-c-mf-nv-r"><source book="Sihler" /> p. 290</footnote>
        <footnote id="sg-c-mf-nv-rl"><source book="Sihler" /> p. 290, 304</footnote>
        <footnote id="sg-c-mf-ro-NV"><source book="Sihler" /> p. 293, 309</footnote>
        <footnote id="sg-c-mf-nv-n"><source book="Sihler" /> p. 290, 295-296</footnote>
        <footnote id="sg-c-mf-n-freak"><source book="Sihler" /> p. 296</footnote>
        <footnote id="sg-c-mf-nv-g"><source book="Sihler" /> p. 204, 283</footnote>
        <footnote id="sg-c-mf-ac"><source book="Fortson" /> p. 277, <source book="Sihler" /> p. 96, 284</footnote>
        <footnote id="sg-i-mf--"><source book="Sihler" /> p. 315-316</footnote>
        <footnote id="sg-i-mf-Cr"><source book="Sihler" /> p. 70, 315</footnote>
        <footnote id="sg-i-mf-ndntrt"><source book="Sihler" /> p. 316</footnote>
        <footnote id="sg-i-mf-ac"><source book="Sihler" /> p. 316</footnote>
        <footnote id="sg-i-n"><source book="Sihler" /> p. 316</footnote>
        <footnote id="sg-i-n-poly"><source book="Sihler" /> p. 69, 316</footnote>
        <footnote id="sg-c-d"><source book="Sihler" /> p. 70, 284</footnote>
        <footnote id="sg-i-d"><source book="Sihler" /> p. 70, 316</footnote>
        <footnote id="sg-i-ab0"><source book="Sihler" /> p. 317</footnote>
        <footnote id="sg-i-ab"><source book="Sihler" /> p. 228, 317-318</footnote>
        <footnote id="sg-i-g"><source book="Sihler" /> p. 316-318</footnote>
        <footnote id="sg-c-ab0"><source book="Sihler" /> p. 285, <source book="Fortson" /> p. 281, <source book="ClacksonHorrocks" /> p. 15-16</footnote>
        <footnote id="sg-c-ab"><source book="Sihler" /> p. 285, <source book="ClacksonHorrocks" /> p. 15-16</footnote>
        <footnote id="sg-c-g"><source book="Sihler" /> p. 285</footnote>
        <footnote id="sg-c-l0"><source book="Sihler" /> p. 253, 285, <source book="ClacksonHorrocks" /> p. 14-16</footnote>
        <footnote id="sg-c-l"><source book="Sihler" /> p. 253, 285, <source book="Fortson" /> p. 281, 286, <source book="ClacksonHorrocks" /> p. 14-16</footnote>
        <footnote id="sg-a-n0"><source book="Sihler" /> p. 266-267</footnote>
        <footnote id="sg-a-v0"><source book="Sihler" /> p. 267-268</footnote>
        <footnote id="sg-a-n"><source book="Sihler" /> p. 78, 266-267</footnote>
        <footnote id="sg-a-v"><source book="Sihler" /> p. 78, 267-268</footnote>
        <footnote id="sg-a-ac"><source book="Sihler" /> p. 78, 267-268</footnote>
        <footnote id="sg-a-d"><source book="Sihler" /> p. 70, 267-268</footnote>
        <footnote id="sg-a-ab0"><source book="Sihler" /> p. 258, 267, 269</footnote>
        <footnote id="sg-a-ab"><source book="Sihler" /> p. 228, 267, 269</footnote>
        <footnote id="sg-a-g"><source book="Sihler" /> p. 267, 269</footnote>
        <footnote id="sg-a-l"><source book="Sihler" /> p. 270</footnote>
        <footnote id="sg-o-mf-n"><source book="Sihler" /> p. 250, 256</footnote>
        <footnote id="sg-ro-mf-n"><source book="Sihler" /> p. 70, 256</footnote>
        <footnote id="sg-o-n-ac"><source book="Sihler" /> p. 250, 258</footnote>
        <footnote id="sg-o-d"><source book="Sihler" /> p. 58-59, 258</footnote>
        <footnote id="sg-o-ab0"><source book="Sihler" /> p. 228, 250-251, 258</footnote>
        <footnote id="sg-o-ab"><source book="Sihler" /> p. 228, 258</footnote>
        <footnote id="sg-o-gA"><source book="Sihler" /> p. 259</footnote>
        <footnote id="sg-o-gB"><source book="Sihler" /> p. 260</footnote>
        <footnote id="sg-o-l"><source book="Sihler" /> p. 260</footnote>
        <footnote id="pl-a-n"><source book="Sihler" /> p. 270-271</footnote>
        <footnote id="pl-a-ac"><source book="Sihler" /> p. 270-271</footnote>
        <footnote id="pl-a-dab"><source book="Sihler" /> p. 270, 272</footnote>
        <footnote id="pl-a-g"><source book="Sihler" /> p. 270, 272</footnote>
        <footnote id="pl-o-mf-n"><source book="Sihler" /> p. 260</footnote>
        <footnote id="pl-o-mf-ac"><source book="Sihler" /> p. 215, 254, 263</footnote>
        <footnote id="pl-o-n-ac"><source book="Sihler" /> p. 78, 263</footnote>
        <footnote id="pl-o-dab"><source book="Sihler" /> p. 263</footnote>
        <footnote id="pl-o-g0"><source book="Sihler" /> p. 264</footnote>
        <footnote id="pl-o-g"><source book="Sihler" /> p. 264-265</footnote>
        <footnote id="pl-c-ac"><source book="Sihler" /> p. 286</footnote>
        <footnote id="pl-c-nv"><source book="Sihler" /> p. 286</footnote>
        <footnote id="pl-c-n"><source book="Sihler" /> p. 286</footnote>
        <footnote id="pl-c-dab0"><source book="Sihler" /> p. 145, 147, 286</footnote>
        <footnote id="pl-c-dab"><source book="Sihler" /> p. 286</footnote>
        <footnote id="pl-c-g0"><source book="Sihler" /> p. 78, 286</footnote>
        <footnote id="pl-c-g"><source book="Sihler" /> p. 66, 286</footnote>
        <footnote id="pl-i-n"><source book="Sihler" /> p. 317</footnote>
        <footnote id="pl-i-nv"><source book="Sihler" /> p. 188, 317</footnote>
        <footnote id="pl-i-nvac"><source book="Sihler" /> p. 188, 317</footnote>
        <footnote id="pl-i-ac"><source book="Sihler" /> p. 317</footnote>
        <footnote id="pl-i-dab"><source book="Sihler" /> p. 318</footnote>
        <footnote id="pl-i-g"><source book="Sihler" /> p. 318</footnote>
    </footnotes>
    <bibliography>
        <book id="ClacksonHorrocks" title="Clackson/Horrocks 2007">Clackson, James / Horrocks, Geoffrey: The Blackwell History of the Latin Language. Blackwell 2007.</book>
        <book id="Fortson" title="Fortson 2010">Fortson, Benjamin W.: Indo-European Language and Culture: an Introduction. Second Edition. Blackwell 2010.</book>
        <book id="Sihler" title="Sihler 1995">Sihler, Andrew L.: New Comparative Grammar of Greek and Latin. Oxford University Press 1995.</book>
    </bibliography>
</grammar_tables>
